autodistill_grounded_sam/__init__.py
autodistill_grounded_sam/grounded_sam.py
autodistill_grounded_sam/helpers.py
autodistll_grounded_sam-0.0.5.dist-info/METADATA
autodistll_grounded_sam-0.0.5.dist-info/WHEEL
autodistll_grounded_sam-0.0.5.dist-info/top_level.txt
autodistll_grounded_sam-0.0.5.dist-info/RECORD
