Metadata-Version: 2.1
Name: autodistll-grounded-sam
Version: 0.0.5
Summary: Automatically distill large foundational models into smaller, in-domain models for deployment
Home-page: https://github.com/autodistill/autodistill
Author: Roboflow
Author-email: jacob@roboflow.com
License: UNKNOWN
Platform: UNKNOWN
Classifier: Programming Language :: Python :: 3
Classifier: License :: OSI Approved :: MIT License
Classifier: Operating System :: OS Independent
Requires-Python: >=3.7
Requires-Dist: numpy (==1.24.2)
Provides-Extra: dev
Requires-Dist: black (==22.3.0) ; extra == 'dev'
Requires-Dist: flake8 ; extra == 'dev'
Requires-Dist: isort ; extra == 'dev'
Requires-Dist: pytest ; extra == 'dev'
Requires-Dist: twine ; extra == 'dev'
Requires-Dist: wheel ; extra == 'dev'
